{
  "base_price": 3995,
  "beamstation_catalog_url": "https://beamstation.com/datasets",
  "beamstation_origin": "https://beamstation.com",
  "category_group_name": "Restaurants",
  "config_category": "social",
  "config_description": "--The \"Crisis\" List--\nBusinesses in saturated markets (high intensity) with weak social presence. They must market or they will die. \n\nHighest conversion leads.\n\nHigh urgency score means they are drowning in a crowded market.\n\nBusiness activity in the last 90 days validated by an \"Active Heartbeat\" signal.",
  "config_name": "Top 300 Restaurant Social Urgency Leads in Denver, Colorado, US",
  "export_job_id": "8114257c-f1bf-47ef-a2d4-9736d529bb15",
  "github_org": "Beamstation-Datasets",
  "id_short": 966439,
  "location_name": "Denver",
  "location_type": "city",
  "repo_name": "top-300-restaurant-social-urgency-leads-in-denver-colorado-us-sample-966439",
  "sample_b2_path": "b2-export:BeamStation-ExportFiles/966439/beamstation_966439_restaurants-us-co_SAMPLE_DIST.csv",
  "sample_pct": 10.0,
  "sample_records": 30,
  "sample_sha256": "e390b98b0c3cc1ceedfd3201eb5bb1ae0856a51c27c8a8ef76952f7f1612494d",
  "sample_size_bytes": 122243,
  "total_records": 300,
  "updated_at": "2026-04-14T21:21:19.377406+00:00"
}